__init__.py
address.py
earthquakequery.py
geocode.py
location.py
result_collection.py
single_result.py
timeframe.py
pyearthquake/__init__.py
pyearthquake/address.py
pyearthquake/earthquake_query.py
pyearthquake/earthquakequery.py
pyearthquake/geocode.py
pyearthquake/key.py
pyearthquake/location.py
pyearthquake/result_collection.py
pyearthquake/single_result.py
pyearthquake/timeframe.py
pyearthquake/enum/__init__.py
pyearthquake/enum/alertlevel.py
pyearthquake/enum/catalog.py
pyearthquake/enum/contributor.py
pyearthquake/enum/delete.py
pyearthquake/enum/magnitude.py
pyearthquake/enum/nodata.py
pyearthquake/enum/origin.py
pyearthquake/enum/supersede.py
pyquakes/__init__.py
pyquakes/address.py
pyquakes/earthquake_query.py
pyquakes/geocode.py
pyquakes/key.py
pyquakes/location.py
pyquakes/result_collection.py
pyquakes/single_result.py
pyquakes/timeframe.py
pyquakes/enum/__init__.py
pyquakes/enum/alertlevel.py
pyquakes/enum/catalog.py
pyquakes/enum/contributor.py
pyquakes/enum/delete.py
pyquakes/enum/magnitude.py
pyquakes/enum/nodata.py
pyquakes/enum/origin.py
pyquakes/enum/supersede.py
pyquakes-0.0.1.dist-info/LICENSE.txt
pyquakes-0.0.1.dist-info/METADATA
pyquakes-0.0.1.dist-info/WHEEL
pyquakes-0.0.1.dist-info/top_level.txt
pyquakes-0.0.1.dist-info/RECORD
