Metadata-Version: 2.1
Name: pyquakes
Version: 0.0.1
Summary: PyQuakes is a Python wrapper for USGS Earthquake Catalog API that manages data querying and result processing.
Home-page: https://github.com/shenjianan97/PyEarthquake
Author: Jianan Shen, Chen Mo
Author-email: shenjianan97@gmail.com
License: UNKNOWN
Platform: UNKNOWN
Requires-Dist: requests (>=2.15.0)
